talk2data_sdk/__init__.py
talk2data_sdk/connector/__init__.py
talk2data_sdk/connector/talk2data_connector.py
talk2data_sdk/constants.py
talk2data_sdk/database/__init__.py
talk2data_sdk/database/database.py
talk2data_sdk/database/gene_annotation.py
talk2data_sdk/logging.py
talk2data_sdk/utils/__init__.py
talk2data_sdk/utils/requests.py
talk2data_sdk-0.1.3.dist-info/METADATA
talk2data_sdk-0.1.3.dist-info/WHEEL
talk2data_sdk-0.1.3.dist-info/RECORD
