Metadata-Version: 2.1
Name: talk2data-sdk
Version: 0.1.3
Summary: A set of python modules for accessing Bioturing's Talk2Data
Author: BioTuring
Author-email: support@bioturing.com
Requires-Python: >=3.10,<4.0
Classifier: Programming Language :: Python :: 3
Classifier: Programming Language :: Python :: 3.10
Classifier: Programming Language :: Python :: 3.11
Classifier: Programming Language :: Python :: 3.12
Classifier: Programming Language :: Python :: 3.13
Requires-Dist: numpy
Requires-Dist: pandas
Requires-Dist: pydantic
Requires-Dist: requests
